yating_tts_sdk_python/__init__.py
Yating_TTS_SDK_Python-1.0.4.dist-info/LICENSE
Yating_TTS_SDK_Python-1.0.4.dist-info/METADATA
Yating_TTS_SDK_Python-1.0.4.dist-info/WHEEL
Yating_TTS_SDK_Python-1.0.4.dist-info/top_level.txt
Yating_TTS_SDK_Python-1.0.4.dist-info/RECORD
