Metadata-Version: 2.1
Name: Yating-TTS-SDK-Python
Version: 1.0.4
Summary: Yating TTS SDK Python
Home-page: https://github.com/pinkeyu7/yating-tts-sdk-python
Author: pinkeyu7
Author-email: pinke.yu7@gmail.com
Keywords: text to speech
Requires-Python: >=3.6
License-File: LICENSE
Requires-Dist: requests >=2.22.0
